arch.py
generator.py
setup.py
arch_gen/__init__.py
areactpy-0.0.1.dist-info/METADATA
areactpy-0.0.1.dist-info/WHEEL
areactpy-0.0.1.dist-info/licenses/LICENSE
areactpy-0.0.1.dist-info/RECORD
