Metadata-Version: 2.1
Name: areactpy
Version: 0.0.1
Summary: An arch reactor package
Author: A React
License-File: LICENSE
Classifier: License :: OSI Approved :: MIT License
Classifier: Operating System :: OS Independent
Classifier: Programming Language :: Python :: 3
Requires-Python: >=3.7
